kilobaik_logging/__init__.py
kilobaik_logging/core/__init__.py
kilobaik_logging-0.1.dist-info/DESCRIPTION.rst
kilobaik_logging-0.1.dist-info/METADATA
kilobaik_logging-0.1.dist-info/RECORD
kilobaik_logging-0.1.dist-info/WHEEL
kilobaik_logging-0.1.dist-info/metadata.json
kilobaik_logging-0.1.dist-info/top_level.txt
